{% load templatetags %}<eSocial xmlns="{{ xmlns }}">{% for s2300_evttsvinicio in s2300_evttsvinicio_lista %}{% ifequal 1 1 %}<evtTSVInicio Id="{{ s2300_evttsvinicio.identidade }}">{% if versao in 'v02_04_02;v02_05_00;NDE1_NDE2' %}<ideEvento>{% if versao in 'v02_04_02;v02_05_00;NDE1_NDE2' %}{% if s2300_evttsvinicio.indretif or s2300_evttsvinicio.indretif == 0 %}<indRetif>{{ s2300_evttsvinicio.indretif|to_xml:"esocial|N" }}</indRetif>{% endif %}{% endif %}{% if versao in 'v02_04_02;v02_05_00;NDE1_NDE2' %}{% if s2300_evttsvinicio.nrrecibo or s2300_evttsvinicio.nrrecibo == 0 %}<nrRecibo>{{ s2300_evttsvinicio.nrrecibo|to_xml:"esocial|C" }}</nrRecibo>{% endif %}{% endif %}{% if versao in 'v02_04_02;v02_05_00;NDE1_NDE2' %}{% if s2300_evttsvinicio.tpamb or s2300_evttsvinicio.tpamb == 0 %}<tpAmb>{{ s2300_evttsvinicio.tpamb|to_xml:"esocial|N" }}</tpAmb>{% endif %}{% endif %}{% if versao in 'v02_04_02;v02_05_00;NDE1_NDE2' %}{% if s2300_evttsvinicio.procemi or s2300_evttsvinicio.procemi == 0 %}<procEmi>{{ s2300_evttsvinicio.procemi|to_xml:"esocial|N" }}</procEmi>{% endif %}{% endif %}{% if versao in 'v02_04_02;v02_05_00;NDE1_NDE2' %}{% if s2300_evttsvinicio.verproc or s2300_evttsvinicio.verproc == 0 %}<verProc>{{ s2300_evttsvinicio.verproc|to_xml:"esocial|C" }}</verProc>{% endif %}{% endif %}</ideEvento>{% endif %}{% if versao in 'v02_04_02;v02_05_00;NDE1_NDE2' %}<ideEmpregador>{% if versao in 'v02_04_02;v02_05_00;NDE1_NDE2' %}{% if s2300_evttsvinicio.tpinsc or s2300_evttsvinicio.tpinsc == 0 %}<tpInsc>{{ s2300_evttsvinicio.tpinsc|to_xml:"esocial|N" }}</tpInsc>{% endif %}{% endif %}{% if versao in 'v02_04_02;v02_05_00;NDE1_NDE2' %}{% if s2300_evttsvinicio.nrinsc or s2300_evttsvinicio.nrinsc == 0 %}<nrInsc>{{ s2300_evttsvinicio.nrinsc|to_xml:"esocial|C" }}</nrInsc>{% endif %}{% endif %}</ideEmpregador>{% endif %}{% if versao in 'v02_04_02;v02_05_00;NDE1_NDE2' %}<trabalhador>{% if versao in 'v02_04_02;v02_05_00;NDE1_NDE2' %}{% if s2300_evttsvinicio.cpftrab or s2300_evttsvinicio.cpftrab == 0 %}<cpfTrab>{{ s2300_evttsvinicio.cpftrab|to_xml:"esocial|C" }}</cpfTrab>{% endif %}{% endif %}{% if versao in 'v02_04_02;v02_05_00;NDE1_NDE2' %}{% if s2300_evttsvinicio.nistrab or s2300_evttsvinicio.nistrab == 0 %}<nisTrab>{{ s2300_evttsvinicio.nistrab|to_xml:"esocial|C" }}</nisTrab>{% endif %}{% endif %}{% if versao in 'v02_04_02;v02_05_00;NDE1_NDE2' %}{% if s2300_evttsvinicio.nmtrab or s2300_evttsvinicio.nmtrab == 0 %}<nmTrab>{{ s2300_evttsvinicio.nmtrab|to_xml:"esocial|C" }}</nmTrab>{% endif %}{% endif %}{% if versao in 'v02_04_02;v02_05_00;NDE1_NDE2' %}{% if s2300_evttsvinicio.sexo or s2300_evttsvinicio.sexo == 0 %}<sexo>{{ s2300_evttsvinicio.sexo|to_xml:"esocial|C" }}</sexo>{% endif %}{% endif %}{% if versao in 'v02_04_02;v02_05_00;NDE1_NDE2' %}{% if s2300_evttsvinicio.racacor or s2300_evttsvinicio.racacor == 0 %}<racaCor>{{ s2300_evttsvinicio.racacor|to_xml:"esocial|N" }}</racaCor>{% endif %}{% endif %}{% if versao in 'v02_04_02;v02_05_00;NDE1_NDE2' %}{% if s2300_evttsvinicio.estciv or s2300_evttsvinicio.estciv == 0 %}<estCiv>{{ s2300_evttsvinicio.estciv|to_xml:"esocial|N" }}</estCiv>{% endif %}{% endif %}{% if versao in 'v02_04_02;v02_05_00;NDE1_NDE2' %}{% if s2300_evttsvinicio.grauinstr or s2300_evttsvinicio.grauinstr == 0 %}<grauInstr>{{ s2300_evttsvinicio.grauinstr|to_xml:"esocial|C" }}</grauInstr>{% endif %}{% endif %}{% if versao in 'v02_04_02;v02_05_00;NDE1_NDE2' %}{% if s2300_evttsvinicio.nmsoc or s2300_evttsvinicio.nmsoc == 0 %}<nmSoc>{{ s2300_evttsvinicio.nmsoc|to_xml:"esocial|C" }}</nmSoc>{% endif %}{% endif %}{% if versao in 'v02_04_02;v02_05_00;NDE1_NDE2' %}<nascimento>{% if versao in 'v02_04_02;v02_05_00;NDE1_NDE2' %}{% if s2300_evttsvinicio.dtnascto or s2300_evttsvinicio.dtnascto == 0 %}<dtNascto>{{ s2300_evttsvinicio.dtnascto|date:"Y-m-d" }}</dtNascto>{% endif %}{% endif %}{% if versao in 'v02_04_02;v02_05_00;NDE1_NDE2' %}{% if s2300_evttsvinicio.codmunic or s2300_evttsvinicio.codmunic == 0 %}<codMunic>{{ s2300_evttsvinicio.codmunic|to_xml:"esocial|N" }}</codMunic>{% endif %}{% endif %}{% if versao in 'v02_04_02;v02_05_00;NDE1_NDE2' %}{% if s2300_evttsvinicio.uf or s2300_evttsvinicio.uf == 0 %}<uf>{{ s2300_evttsvinicio.uf|to_xml:"esocial|C" }}</uf>{% endif %}{% endif %}{% if versao in 'v02_04_02;v02_05_00;NDE1_NDE2' %}{% if s2300_evttsvinicio.paisnascto or s2300_evttsvinicio.paisnascto == 0 %}<paisNascto>{{ s2300_evttsvinicio.paisnascto|to_xml:"esocial|C" }}</paisNascto>{% endif %}{% endif %}{% if versao in 'v02_04_02;v02_05_00;NDE1_NDE2' %}{% if s2300_evttsvinicio.paisnac or s2300_evttsvinicio.paisnac == 0 %}<paisNac>{{ s2300_evttsvinicio.paisnac|to_xml:"esocial|C" }}</paisNac>{% endif %}{% endif %}{% if versao in 'v02_04_02;v02_05_00;NDE1_NDE2' %}{% if s2300_evttsvinicio.nmmae or s2300_evttsvinicio.nmmae == 0 %}<nmMae>{{ s2300_evttsvinicio.nmmae|to_xml:"esocial|C" }}</nmMae>{% endif %}{% endif %}{% if versao in 'v02_04_02;v02_05_00;NDE1_NDE2' %}{% if s2300_evttsvinicio.nmpai or s2300_evttsvinicio.nmpai == 0 %}<nmPai>{{ s2300_evttsvinicio.nmpai|to_xml:"esocial|C" }}</nmPai>{% endif %}{% endif %}</nascimento>{% endif %}{% if versao in 'v02_04_02;v02_05_00;NDE1_NDE2' %}{% query s2300_documentos_lista s2300_evttsvinicio=s2300_evttsvinicio as s2300_documentos_lista_filtro %}{% for s2300_documentos in s2300_documentos_lista_filtro %}{% ifequal s2300_documentos.s2300_evttsvinicio.id s2300_evttsvinicio.id %}<documentos>{% if versao in 'v02_04_02;v02_05_00;NDE1_NDE2' %}{% query s2300_ctps_lista s2300_documentos=s2300_documentos as s2300_ctps_lista_filtro %}{% for s2300_ctps in s2300_ctps_lista_filtro %}{% ifequal s2300_ctps.s2300_documentos.id s2300_documentos.id %}<CTPS>{% if versao in 'v02_04_02;v02_05_00;NDE1_NDE2' %}{% if s2300_ctps.nrctps or s2300_ctps.nrctps == 0 %}<nrCtps>{{ s2300_ctps.nrctps|to_xml:"esocial|C" }}</nrCtps>{% endif %}{% endif %}{% if versao in 'v02_04_02;v02_05_00;NDE1_NDE2' %}{% if s2300_ctps.seriectps or s2300_ctps.seriectps == 0 %}<serieCtps>{{ s2300_ctps.seriectps|to_xml:"esocial|C" }}</serieCtps>{% endif %}{% endif %}{% if versao in 'v02_04_02;v02_05_00;NDE1_NDE2' %}{% if s2300_ctps.ufctps or s2300_ctps.ufctps == 0 %}<ufCtps>{{ s2300_ctps.ufctps|to_xml:"esocial|C" }}</ufCtps>{% endif %}{% endif %}</CTPS>{% endifequal %}{% endfor %}{% endif %}{% if versao in 'v02_04_02;v02_05_00;NDE1_NDE2' %}{% query s2300_ric_lista s2300_documentos=s2300_documentos as s2300_ric_lista_filtro %}{% for s2300_ric in s2300_ric_lista_filtro %}{% ifequal s2300_ric.s2300_documentos.id s2300_documentos.id %}<RIC>{% if versao in 'v02_04_02;v02_05_00;NDE1_NDE2' %}{% if s2300_ric.nrric or s2300_ric.nrric == 0 %}<nrRic>{{ s2300_ric.nrric|to_xml:"esocial|C" }}</nrRic>{% endif %}{% endif %}{% if versao in 'v02_04_02;v02_05_00;NDE1_NDE2' %}{% if s2300_ric.orgaoemissor or s2300_ric.orgaoemissor == 0 %}<orgaoEmissor>{{ s2300_ric.orgaoemissor|to_xml:"esocial|C" }}</orgaoEmissor>{% endif %}{% endif %}{% if versao in 'v02_04_02;v02_05_00;NDE1_NDE2' %}{% if s2300_ric.dtexped or s2300_ric.dtexped == 0 %}<dtExped>{{ s2300_ric.dtexped|date:"Y-m-d" }}</dtExped>{% endif %}{% endif %}</RIC>{% endifequal %}{% endfor %}{% endif %}{% if versao in 'v02_04_02;v02_05_00;NDE1_NDE2' %}{% query s2300_rg_lista s2300_documentos=s2300_documentos as s2300_rg_lista_filtro %}{% for s2300_rg in s2300_rg_lista_filtro %}{% ifequal s2300_rg.s2300_documentos.id s2300_documentos.id %}<RG>{% if versao in 'v02_04_02;v02_05_00;NDE1_NDE2' %}{% if s2300_rg.nrrg or s2300_rg.nrrg == 0 %}<nrRg>{{ s2300_rg.nrrg|to_xml:"esocial|C" }}</nrRg>{% endif %}{% endif %}{% if versao in 'v02_04_02;v02_05_00;NDE1_NDE2' %}{% if s2300_rg.orgaoemissor or s2300_rg.orgaoemissor == 0 %}<orgaoEmissor>{{ s2300_rg.orgaoemissor|to_xml:"esocial|C" }}</orgaoEmissor>{% endif %}{% endif %}{% if versao in 'v02_04_02;v02_05_00;NDE1_NDE2' %}{% if s2300_rg.dtexped or s2300_rg.dtexped == 0 %}<dtExped>{{ s2300_rg.dtexped|date:"Y-m-d" }}</dtExped>{% endif %}{% endif %}</RG>{% endifequal %}{% endfor %}{% endif %}{% if versao in 'v02_04_02;v02_05_00;NDE1_NDE2' %}{% query s2300_rne_lista s2300_documentos=s2300_documentos as s2300_rne_lista_filtro %}{% for s2300_rne in s2300_rne_lista_filtro %}{% ifequal s2300_rne.s2300_documentos.id s2300_documentos.id %}<RNE>{% if versao in 'v02_04_02;v02_05_00;NDE1_NDE2' %}{% if s2300_rne.nrrne or s2300_rne.nrrne == 0 %}<nrRne>{{ s2300_rne.nrrne|to_xml:"esocial|C" }}</nrRne>{% endif %}{% endif %}{% if versao in 'v02_04_02;v02_05_00;NDE1_NDE2' %}{% if s2300_rne.orgaoemissor or s2300_rne.orgaoemissor == 0 %}<orgaoEmissor>{{ s2300_rne.orgaoemissor|to_xml:"esocial|C" }}</orgaoEmissor>{% endif %}{% endif %}{% if versao in 'v02_04_02;v02_05_00;NDE1_NDE2' %}{% if s2300_rne.dtexped or s2300_rne.dtexped == 0 %}<dtExped>{{ s2300_rne.dtexped|date:"Y-m-d" }}</dtExped>{% endif %}{% endif %}</RNE>{% endifequal %}{% endfor %}{% endif %}{% if versao in 'v02_04_02;v02_05_00;NDE1_NDE2' %}{% query s2300_oc_lista s2300_documentos=s2300_documentos as s2300_oc_lista_filtro %}{% for s2300_oc in s2300_oc_lista_filtro %}{% ifequal s2300_oc.s2300_documentos.id s2300_documentos.id %}<OC>{% if versao in 'v02_04_02;v02_05_00;NDE1_NDE2' %}{% if s2300_oc.nroc or s2300_oc.nroc == 0 %}<nrOc>{{ s2300_oc.nroc|to_xml:"esocial|C" }}</nrOc>{% endif %}{% endif %}{% if versao in 'v02_04_02;v02_05_00;NDE1_NDE2' %}{% if s2300_oc.orgaoemissor or s2300_oc.orgaoemissor == 0 %}<orgaoEmissor>{{ s2300_oc.orgaoemissor|to_xml:"esocial|C" }}</orgaoEmissor>{% endif %}{% endif %}{% if versao in 'v02_04_02;v02_05_00;NDE1_NDE2' %}{% if s2300_oc.dtexped or s2300_oc.dtexped == 0 %}<dtExped>{{ s2300_oc.dtexped|date:"Y-m-d" }}</dtExped>{% endif %}{% endif %}{% if versao in 'v02_04_02;v02_05_00;NDE1_NDE2' %}{% if s2300_oc.dtvalid or s2300_oc.dtvalid == 0 %}<dtValid>{{ s2300_oc.dtvalid|date:"Y-m-d" }}</dtValid>{% endif %}{% endif %}</OC>{% endifequal %}{% endfor %}{% endif %}{% if versao in 'v02_04_02;v02_05_00;NDE1_NDE2' %}{% query s2300_cnh_lista s2300_documentos=s2300_documentos as s2300_cnh_lista_filtro %}{% for s2300_cnh in s2300_cnh_lista_filtro %}{% ifequal s2300_cnh.s2300_documentos.id s2300_documentos.id %}<CNH>{% if versao in 'v02_04_02;v02_05_00;NDE1_NDE2' %}{% if s2300_cnh.nrregcnh or s2300_cnh.nrregcnh == 0 %}<nrRegCnh>{{ s2300_cnh.nrregcnh|to_xml:"esocial|C" }}</nrRegCnh>{% endif %}{% endif %}{% if versao in 'v02_04_02;v02_05_00;NDE1_NDE2' %}{% if s2300_cnh.dtexped or s2300_cnh.dtexped == 0 %}<dtExped>{{ s2300_cnh.dtexped|date:"Y-m-d" }}</dtExped>{% endif %}{% endif %}{% if versao in 'v02_04_02;v02_05_00;NDE1_NDE2' %}{% if s2300_cnh.ufcnh or s2300_cnh.ufcnh == 0 %}<ufCnh>{{ s2300_cnh.ufcnh|to_xml:"esocial|C" }}</ufCnh>{% endif %}{% endif %}{% if versao in 'v02_04_02;v02_05_00;NDE1_NDE2' %}{% if s2300_cnh.dtvalid or s2300_cnh.dtvalid == 0 %}<dtValid>{{ s2300_cnh.dtvalid|date:"Y-m-d" }}</dtValid>{% endif %}{% endif %}{% if versao in 'v02_04_02;v02_05_00;NDE1_NDE2' %}{% if s2300_cnh.dtprihab or s2300_cnh.dtprihab == 0 %}<dtPriHab>{{ s2300_cnh.dtprihab|date:"Y-m-d" }}</dtPriHab>{% endif %}{% endif %}{% if versao in 'v02_04_02;v02_05_00;NDE1_NDE2' %}{% if s2300_cnh.categoriacnh or s2300_cnh.categoriacnh == 0 %}<categoriaCnh>{{ s2300_cnh.categoriacnh|to_xml:"esocial|C" }}</categoriaCnh>{% endif %}{% endif %}</CNH>{% endifequal %}{% endfor %}{% endif %}</documentos>{% endifequal %}{% endfor %}{% endif %}{% if versao in 'v02_04_02;v02_05_00;NDE1_NDE2' %}<endereco>{% if versao in 'v02_04_02;v02_05_00;NDE1_NDE2' %}{% query s2300_brasil_lista s2300_evttsvinicio=s2300_evttsvinicio as s2300_brasil_lista_filtro %}{% for s2300_brasil in s2300_brasil_lista_filtro %}{% ifequal s2300_brasil.s2300_evttsvinicio.id s2300_evttsvinicio.id %}<brasil>{% if versao in 'v02_04_02;v02_05_00;NDE1_NDE2' %}{% if s2300_brasil.tplograd or s2300_brasil.tplograd == 0 %}<tpLograd>{{ s2300_brasil.tplograd|to_xml:"esocial|C" }}</tpLograd>{% endif %}{% endif %}{% if versao in 'v02_04_02;v02_05_00;NDE1_NDE2' %}{% if s2300_brasil.dsclograd or s2300_brasil.dsclograd == 0 %}<dscLograd>{{ s2300_brasil.dsclograd|to_xml:"esocial|C" }}</dscLograd>{% endif %}{% endif %}{% if versao in 'v02_04_02;v02_05_00;NDE1_NDE2' %}{% if s2300_brasil.nrlograd or s2300_brasil.nrlograd == 0 %}<nrLograd>{{ s2300_brasil.nrlograd|to_xml:"esocial|C" }}</nrLograd>{% endif %}{% endif %}{% if versao in 'v02_04_02;v02_05_00;NDE1_NDE2' %}{% if s2300_brasil.complemento or s2300_brasil.complemento == 0 %}<complemento>{{ s2300_brasil.complemento|to_xml:"esocial|C" }}</complemento>{% endif %}{% endif %}{% if versao in 'v02_04_02;v02_05_00;NDE1_NDE2' %}{% if s2300_brasil.bairro or s2300_brasil.bairro == 0 %}<bairro>{{ s2300_brasil.bairro|to_xml:"esocial|C" }}</bairro>{% endif %}{% endif %}{% if versao in 'v02_04_02;v02_05_00;NDE1_NDE2' %}{% if s2300_brasil.cep or s2300_brasil.cep == 0 %}<cep>{{ s2300_brasil.cep|to_xml:"esocial|C" }}</cep>{% endif %}{% endif %}{% if versao in 'v02_04_02;v02_05_00;NDE1_NDE2' %}{% if s2300_brasil.codmunic or s2300_brasil.codmunic == 0 %}<codMunic>{{ s2300_brasil.codmunic|to_xml:"esocial|N" }}</codMunic>{% endif %}{% endif %}{% if versao in 'v02_04_02;v02_05_00;NDE1_NDE2' %}{% if s2300_brasil.uf or s2300_brasil.uf == 0 %}<uf>{{ s2300_brasil.uf|to_xml:"esocial|C" }}</uf>{% endif %}{% endif %}</brasil>{% endifequal %}{% endfor %}{% endif %}{% if versao in 'v02_04_02;v02_05_00;NDE1_NDE2' %}{% query s2300_exterior_lista s2300_evttsvinicio=s2300_evttsvinicio as s2300_exterior_lista_filtro %}{% for s2300_exterior in s2300_exterior_lista_filtro %}{% ifequal s2300_exterior.s2300_evttsvinicio.id s2300_evttsvinicio.id %}<exterior>{% if versao in 'v02_04_02;v02_05_00;NDE1_NDE2' %}{% if s2300_exterior.paisresid or s2300_exterior.paisresid == 0 %}<paisResid>{{ s2300_exterior.paisresid|to_xml:"esocial|C" }}</paisResid>{% endif %}{% endif %}{% if versao in 'v02_04_02;v02_05_00;NDE1_NDE2' %}{% if s2300_exterior.dsclograd or s2300_exterior.dsclograd == 0 %}<dscLograd>{{ s2300_exterior.dsclograd|to_xml:"esocial|C" }}</dscLograd>{% endif %}{% endif %}{% if versao in 'v02_04_02;v02_05_00;NDE1_NDE2' %}{% if s2300_exterior.nrlograd or s2300_exterior.nrlograd == 0 %}<nrLograd>{{ s2300_exterior.nrlograd|to_xml:"esocial|C" }}</nrLograd>{% endif %}{% endif %}{% if versao in 'v02_04_02;v02_05_00;NDE1_NDE2' %}{% if s2300_exterior.complemento or s2300_exterior.complemento == 0 %}<complemento>{{ s2300_exterior.complemento|to_xml:"esocial|C" }}</complemento>{% endif %}{% endif %}{% if versao in 'v02_04_02;v02_05_00;NDE1_NDE2' %}{% if s2300_exterior.bairro or s2300_exterior.bairro == 0 %}<bairro>{{ s2300_exterior.bairro|to_xml:"esocial|C" }}</bairro>{% endif %}{% endif %}{% if versao in 'v02_04_02;v02_05_00;NDE1_NDE2' %}{% if s2300_exterior.nmcid or s2300_exterior.nmcid == 0 %}<nmCid>{{ s2300_exterior.nmcid|to_xml:"esocial|C" }}</nmCid>{% endif %}{% endif %}{% if versao in 'v02_04_02;v02_05_00;NDE1_NDE2' %}{% if s2300_exterior.codpostal or s2300_exterior.codpostal == 0 %}<codPostal>{{ s2300_exterior.codpostal|to_xml:"esocial|C" }}</codPostal>{% endif %}{% endif %}</exterior>{% endifequal %}{% endfor %}{% endif %}</endereco>{% endif %}{% if versao in 'v02_04_02;v02_05_00;NDE1_NDE2' %}{% query s2300_trabestrangeiro_lista s2300_evttsvinicio=s2300_evttsvinicio as s2300_trabestrangeiro_lista_filtro %}{% for s2300_trabestrangeiro in s2300_trabestrangeiro_lista_filtro %}{% ifequal s2300_trabestrangeiro.s2300_evttsvinicio.id s2300_evttsvinicio.id %}<trabEstrangeiro>{% if versao in 'v02_04_02;v02_05_00;NDE1_NDE2' %}{% if s2300_trabestrangeiro.dtchegada or s2300_trabestrangeiro.dtchegada == 0 %}<dtChegada>{{ s2300_trabestrangeiro.dtchegada|date:"Y-m-d" }}</dtChegada>{% endif %}{% endif %}{% if versao in 'v02_04_02;v02_05_00;NDE1_NDE2' %}{% if s2300_trabestrangeiro.classtrabestrang or s2300_trabestrangeiro.classtrabestrang == 0 %}<classTrabEstrang>{{ s2300_trabestrangeiro.classtrabestrang|to_xml:"esocial|N" }}</classTrabEstrang>{% endif %}{% endif %}{% if versao in 'v02_04_02;v02_05_00;NDE1_NDE2' %}{% if s2300_trabestrangeiro.casadobr or s2300_trabestrangeiro.casadobr == 0 %}<casadoBr>{{ s2300_trabestrangeiro.casadobr|to_xml:"esocial|C" }}</casadoBr>{% endif %}{% endif %}{% if versao in 'v02_04_02;v02_05_00;NDE1_NDE2' %}{% if s2300_trabestrangeiro.filhosbr or s2300_trabestrangeiro.filhosbr == 0 %}<filhosBr>{{ s2300_trabestrangeiro.filhosbr|to_xml:"esocial|C" }}</filhosBr>{% endif %}{% endif %}</trabEstrangeiro>{% endifequal %}{% endfor %}{% endif %}{% if versao in 'v02_04_02;v02_05_00;NDE1_NDE2' %}{% query s2300_infodeficiencia_lista s2300_evttsvinicio=s2300_evttsvinicio as s2300_infodeficiencia_lista_filtro %}{% for s2300_infodeficiencia in s2300_infodeficiencia_lista_filtro %}{% ifequal s2300_infodeficiencia.s2300_evttsvinicio.id s2300_evttsvinicio.id %}<infoDeficiencia>{% if versao in 'v02_04_02;v02_05_00;NDE1_NDE2' %}{% if s2300_infodeficiencia.deffisica or s2300_infodeficiencia.deffisica == 0 %}<defFisica>{{ s2300_infodeficiencia.deffisica|to_xml:"esocial|C" }}</defFisica>{% endif %}{% endif %}{% if versao in 'v02_04_02;v02_05_00;NDE1_NDE2' %}{% if s2300_infodeficiencia.defvisual or s2300_infodeficiencia.defvisual == 0 %}<defVisual>{{ s2300_infodeficiencia.defvisual|to_xml:"esocial|C" }}</defVisual>{% endif %}{% endif %}{% if versao in 'v02_04_02;v02_05_00;NDE1_NDE2' %}{% if s2300_infodeficiencia.defauditiva or s2300_infodeficiencia.defauditiva == 0 %}<defAuditiva>{{ s2300_infodeficiencia.defauditiva|to_xml:"esocial|C" }}</defAuditiva>{% endif %}{% endif %}{% if versao in 'v02_04_02;v02_05_00;NDE1_NDE2' %}{% if s2300_infodeficiencia.defmental or s2300_infodeficiencia.defmental == 0 %}<defMental>{{ s2300_infodeficiencia.defmental|to_xml:"esocial|C" }}</defMental>{% endif %}{% endif %}{% if versao in 'v02_04_02;v02_05_00;NDE1_NDE2' %}{% if s2300_infodeficiencia.defintelectual or s2300_infodeficiencia.defintelectual == 0 %}<defIntelectual>{{ s2300_infodeficiencia.defintelectual|to_xml:"esocial|C" }}</defIntelectual>{% endif %}{% endif %}{% if versao in 'v02_04_02;v02_05_00;NDE1_NDE2' %}{% if s2300_infodeficiencia.reabreadap or s2300_infodeficiencia.reabreadap == 0 %}<reabReadap>{{ s2300_infodeficiencia.reabreadap|to_xml:"esocial|C" }}</reabReadap>{% endif %}{% endif %}{% if versao in 'v02_04_02;v02_05_00;NDE1_NDE2' %}{% if s2300_infodeficiencia.observacao or s2300_infodeficiencia.observacao == 0 %}<observacao>{{ s2300_infodeficiencia.observacao|to_xml:"esocial|C" }}</observacao>{% endif %}{% endif %}</infoDeficiencia>{% endifequal %}{% endfor %}{% endif %}{% if versao in 'v02_04_02;v02_05_00;NDE1_NDE2' %}{% query s2300_dependente_lista s2300_evttsvinicio=s2300_evttsvinicio as s2300_dependente_lista_filtro %}{% for s2300_dependente in s2300_dependente_lista_filtro %}{% ifequal s2300_dependente.s2300_evttsvinicio.id s2300_evttsvinicio.id %}<dependente>{% if versao in 'v02_04_02;v02_05_00;NDE1_NDE2' %}{% if s2300_dependente.tpdep or s2300_dependente.tpdep == 0 %}<tpDep>{{ s2300_dependente.tpdep|to_xml:"esocial|C" }}</tpDep>{% endif %}{% endif %}{% if versao in 'v02_04_02;v02_05_00;NDE1_NDE2' %}{% if s2300_dependente.nmdep or s2300_dependente.nmdep == 0 %}<nmDep>{{ s2300_dependente.nmdep|to_xml:"esocial|C" }}</nmDep>{% endif %}{% endif %}{% if versao in 'v02_04_02;v02_05_00;NDE1_NDE2' %}{% if s2300_dependente.dtnascto or s2300_dependente.dtnascto == 0 %}<dtNascto>{{ s2300_dependente.dtnascto|date:"Y-m-d" }}</dtNascto>{% endif %}{% endif %}{% if versao in 'v02_04_02;v02_05_00;NDE1_NDE2' %}{% if s2300_dependente.cpfdep or s2300_dependente.cpfdep == 0 %}<cpfDep>{{ s2300_dependente.cpfdep|to_xml:"esocial|C" }}</cpfDep>{% endif %}{% endif %}{% if versao in ';;NDE1_NDE2' %}{% if s2300_dependente.sexodep or s2300_dependente.sexodep == 0 %}<sexoDep>{{ s2300_dependente.sexodep|to_xml:"esocial|C" }}</sexoDep>{% endif %}{% endif %}{% if versao in 'v02_04_02;v02_05_00;NDE1_NDE2' %}{% if s2300_dependente.depirrf or s2300_dependente.depirrf == 0 %}<depIRRF>{{ s2300_dependente.depirrf|to_xml:"esocial|C" }}</depIRRF>{% endif %}{% endif %}{% if versao in 'v02_04_02;v02_05_00;NDE1_NDE2' %}{% if s2300_dependente.depsf or s2300_dependente.depsf == 0 %}<depSF>{{ s2300_dependente.depsf|to_xml:"esocial|C" }}</depSF>{% endif %}{% endif %}{% if versao in 'v02_04_02;v02_05_00;NDE1_NDE2' %}{% if s2300_dependente.inctrab or s2300_dependente.inctrab == 0 %}<incTrab>{{ s2300_dependente.inctrab|to_xml:"esocial|C" }}</incTrab>{% endif %}{% endif %}{% if versao in ';;NDE1_NDE2' %}{% if s2300_dependente.depfinsprev or s2300_dependente.depfinsprev == 0 %}<depFinsPrev>{{ s2300_dependente.depfinsprev|to_xml:"esocial|C" }}</depFinsPrev>{% endif %}{% endif %}</dependente>{% endifequal %}{% endfor %}{% endif %}{% if versao in 'v02_04_02;v02_05_00;NDE1_NDE2' %}{% query s2300_contato_lista s2300_evttsvinicio=s2300_evttsvinicio as s2300_contato_lista_filtro %}{% for s2300_contato in s2300_contato_lista_filtro %}{% ifequal s2300_contato.s2300_evttsvinicio.id s2300_evttsvinicio.id %}<contato>{% if versao in 'v02_04_02;v02_05_00;NDE1_NDE2' %}{% if s2300_contato.foneprinc or s2300_contato.foneprinc == 0 %}<fonePrinc>{{ s2300_contato.foneprinc|to_xml:"esocial|C" }}</fonePrinc>{% endif %}{% endif %}{% if versao in 'v02_04_02;v02_05_00;NDE1_NDE2' %}{% if s2300_contato.fonealternat or s2300_contato.fonealternat == 0 %}<foneAlternat>{{ s2300_contato.fonealternat|to_xml:"esocial|C" }}</foneAlternat>{% endif %}{% endif %}{% if versao in 'v02_04_02;v02_05_00;NDE1_NDE2' %}{% if s2300_contato.emailprinc or s2300_contato.emailprinc == 0 %}<emailPrinc>{{ s2300_contato.emailprinc|to_xml:"esocial|C" }}</emailPrinc>{% endif %}{% endif %}{% if versao in 'v02_04_02;v02_05_00;NDE1_NDE2' %}{% if s2300_contato.emailalternat or s2300_contato.emailalternat == 0 %}<emailAlternat>{{ s2300_contato.emailalternat|to_xml:"esocial|C" }}</emailAlternat>{% endif %}{% endif %}</contato>{% endifequal %}{% endfor %}{% endif %}</trabalhador>{% endif %}{% if versao in 'v02_04_02;v02_05_00;NDE1_NDE2' %}<infoTSVInicio>{% if versao in 'v02_04_02;v02_05_00;NDE1_NDE2' %}{% if s2300_evttsvinicio.cadini or s2300_evttsvinicio.cadini == 0 %}<cadIni>{{ s2300_evttsvinicio.cadini|to_xml:"esocial|C" }}</cadIni>{% endif %}{% endif %}{% if versao in 'v02_04_02;v02_05_00;NDE1_NDE2' %}{% if s2300_evttsvinicio.codcateg or s2300_evttsvinicio.codcateg == 0 %}<codCateg>{{ s2300_evttsvinicio.codcateg|to_xml:"esocial|N" }}</codCateg>{% endif %}{% endif %}{% if versao in 'v02_04_02;v02_05_00;NDE1_NDE2' %}{% if s2300_evttsvinicio.dtinicio or s2300_evttsvinicio.dtinicio == 0 %}<dtInicio>{{ s2300_evttsvinicio.dtinicio|date:"Y-m-d" }}</dtInicio>{% endif %}{% endif %}{% if versao in 'v02_04_02;v02_05_00;NDE1_NDE2' %}{% if s2300_evttsvinicio.natatividade or s2300_evttsvinicio.natatividade == 0 %}<natAtividade>{{ s2300_evttsvinicio.natatividade|to_xml:"esocial|N" }}</natAtividade>{% endif %}{% endif %}{% if versao in 'v02_04_02;v02_05_00;NDE1_NDE2' %}{% query s2300_infocomplementares_lista s2300_evttsvinicio=s2300_evttsvinicio as s2300_infocomplementares_lista_filtro %}{% for s2300_infocomplementares in s2300_infocomplementares_lista_filtro %}{% ifequal s2300_infocomplementares.s2300_evttsvinicio.id s2300_evttsvinicio.id %}<infoComplementares>{% if versao in 'v02_04_02;v02_05_00;NDE1_NDE2' %}{% query s2300_cargofuncao_lista s2300_infocomplementares=s2300_infocomplementares as s2300_cargofuncao_lista_filtro %}{% for s2300_cargofuncao in s2300_cargofuncao_lista_filtro %}{% ifequal s2300_cargofuncao.s2300_infocomplementares.id s2300_infocomplementares.id %}<cargoFuncao>{% if versao in 'v02_04_02;v02_05_00;NDE1_NDE2' %}{% if s2300_cargofuncao.codcargo or s2300_cargofuncao.codcargo == 0 %}<codCargo>{{ s2300_cargofuncao.codcargo|to_xml:"esocial|C" }}</codCargo>{% endif %}{% endif %}{% if versao in 'v02_04_02;v02_05_00;NDE1_NDE2' %}{% if s2300_cargofuncao.codfuncao or s2300_cargofuncao.codfuncao == 0 %}<codFuncao>{{ s2300_cargofuncao.codfuncao|to_xml:"esocial|C" }}</codFuncao>{% endif %}{% endif %}</cargoFuncao>{% endifequal %}{% endfor %}{% endif %}{% if versao in 'v02_04_02;v02_05_00;NDE1_NDE2' %}{% query s2300_remuneracao_lista s2300_infocomplementares=s2300_infocomplementares as s2300_remuneracao_lista_filtro %}{% for s2300_remuneracao in s2300_remuneracao_lista_filtro %}{% ifequal s2300_remuneracao.s2300_infocomplementares.id s2300_infocomplementares.id %}<remuneracao>{% if versao in 'v02_04_02;v02_05_00;NDE1_NDE2' %}{% if s2300_remuneracao.vrsalfx or s2300_remuneracao.vrsalfx == 0 %}<vrSalFx>{{ s2300_remuneracao.vrsalfx|to_xml:"esocial|N" }}</vrSalFx>{% endif %}{% endif %}{% if versao in 'v02_04_02;v02_05_00;NDE1_NDE2' %}{% if s2300_remuneracao.undsalfixo or s2300_remuneracao.undsalfixo == 0 %}<undSalFixo>{{ s2300_remuneracao.undsalfixo|to_xml:"esocial|N" }}</undSalFixo>{% endif %}{% endif %}{% if versao in 'v02_04_02;v02_05_00;NDE1_NDE2' %}{% if s2300_remuneracao.dscsalvar or s2300_remuneracao.dscsalvar == 0 %}<dscSalVar>{{ s2300_remuneracao.dscsalvar|to_xml:"esocial|C" }}</dscSalVar>{% endif %}{% endif %}</remuneracao>{% endifequal %}{% endfor %}{% endif %}{% if versao in 'v02_04_02;v02_05_00;NDE1_NDE2' %}{% query s2300_fgts_lista s2300_infocomplementares=s2300_infocomplementares as s2300_fgts_lista_filtro %}{% for s2300_fgts in s2300_fgts_lista_filtro %}{% ifequal s2300_fgts.s2300_infocomplementares.id s2300_infocomplementares.id %}<fgts>{% if versao in 'v02_04_02;v02_05_00;NDE1_NDE2' %}{% if s2300_fgts.opcfgts or s2300_fgts.opcfgts == 0 %}<opcFGTS>{{ s2300_fgts.opcfgts|to_xml:"esocial|N" }}</opcFGTS>{% endif %}{% endif %}{% if versao in 'v02_04_02;v02_05_00;NDE1_NDE2' %}{% if s2300_fgts.dtopcfgts or s2300_fgts.dtopcfgts == 0 %}<dtOpcFGTS>{{ s2300_fgts.dtopcfgts|date:"Y-m-d" }}</dtOpcFGTS>{% endif %}{% endif %}</fgts>{% endifequal %}{% endfor %}{% endif %}{% if versao in 'v02_04_02;v02_05_00;NDE1_NDE2' %}{% query s2300_infodirigentesindical_lista s2300_infocomplementares=s2300_infocomplementares as s2300_infodirigentesindical_lista_filtro %}{% for s2300_infodirigentesindical in s2300_infodirigentesindical_lista_filtro %}{% ifequal s2300_infodirigentesindical.s2300_infocomplementares.id s2300_infocomplementares.id %}<infoDirigenteSindical>{% if versao in 'v02_04_02;v02_05_00;NDE1_NDE2' %}{% if s2300_infodirigentesindical.categorig or s2300_infodirigentesindical.categorig == 0 %}<categOrig>{{ s2300_infodirigentesindical.categorig|to_xml:"esocial|N" }}</categOrig>{% endif %}{% endif %}{% if versao in 'v02_04_02;v02_05_00;NDE1_NDE2' %}{% if s2300_infodirigentesindical.cnpjorigem or s2300_infodirigentesindical.cnpjorigem == 0 %}<cnpjOrigem>{{ s2300_infodirigentesindical.cnpjorigem|to_xml:"esocial|C" }}</cnpjOrigem>{% endif %}{% endif %}{% if versao in 'v02_04_02;v02_05_00;NDE1_NDE2' %}{% if s2300_infodirigentesindical.dtadmorig or s2300_infodirigentesindical.dtadmorig == 0 %}<dtAdmOrig>{{ s2300_infodirigentesindical.dtadmorig|date:"Y-m-d" }}</dtAdmOrig>{% endif %}{% endif %}{% if versao in 'v02_04_02;v02_05_00;NDE1_NDE2' %}{% if s2300_infodirigentesindical.matricorig or s2300_infodirigentesindical.matricorig == 0 %}<matricOrig>{{ s2300_infodirigentesindical.matricorig|to_xml:"esocial|C" }}</matricOrig>{% endif %}{% endif %}</infoDirigenteSindical>{% endifequal %}{% endfor %}{% endif %}{% if versao in 'v02_04_02;v02_05_00;NDE1_NDE2' %}{% query s2300_infotrabcedido_lista s2300_infocomplementares=s2300_infocomplementares as s2300_infotrabcedido_lista_filtro %}{% for s2300_infotrabcedido in s2300_infotrabcedido_lista_filtro %}{% ifequal s2300_infotrabcedido.s2300_infocomplementares.id s2300_infocomplementares.id %}<infoTrabCedido>{% if versao in 'v02_04_02;v02_05_00;NDE1_NDE2' %}{% if s2300_infotrabcedido.categorig or s2300_infotrabcedido.categorig == 0 %}<categOrig>{{ s2300_infotrabcedido.categorig|to_xml:"esocial|N" }}</categOrig>{% endif %}{% endif %}{% if versao in 'v02_04_02;v02_05_00;NDE1_NDE2' %}{% if s2300_infotrabcedido.cnpjcednt or s2300_infotrabcedido.cnpjcednt == 0 %}<cnpjCednt>{{ s2300_infotrabcedido.cnpjcednt|to_xml:"esocial|C" }}</cnpjCednt>{% endif %}{% endif %}{% if versao in 'v02_04_02;v02_05_00;NDE1_NDE2' %}{% if s2300_infotrabcedido.matricced or s2300_infotrabcedido.matricced == 0 %}<matricCed>{{ s2300_infotrabcedido.matricced|to_xml:"esocial|C" }}</matricCed>{% endif %}{% endif %}{% if versao in 'v02_04_02;v02_05_00;NDE1_NDE2' %}{% if s2300_infotrabcedido.dtadmced or s2300_infotrabcedido.dtadmced == 0 %}<dtAdmCed>{{ s2300_infotrabcedido.dtadmced|date:"Y-m-d" }}</dtAdmCed>{% endif %}{% endif %}{% if versao in 'v02_04_02;v02_05_00;NDE1_NDE2' %}{% if s2300_infotrabcedido.tpregtrab or s2300_infotrabcedido.tpregtrab == 0 %}<tpRegTrab>{{ s2300_infotrabcedido.tpregtrab|to_xml:"esocial|N" }}</tpRegTrab>{% endif %}{% endif %}{% if versao in 'v02_04_02;v02_05_00;NDE1_NDE2' %}{% if s2300_infotrabcedido.tpregprev or s2300_infotrabcedido.tpregprev == 0 %}<tpRegPrev>{{ s2300_infotrabcedido.tpregprev|to_xml:"esocial|N" }}</tpRegPrev>{% endif %}{% endif %}{% if versao in 'v02_04_02;v02_05_00;NDE1_NDE2' %}{% if s2300_infotrabcedido.infonus or s2300_infotrabcedido.infonus == 0 %}<infOnus>{{ s2300_infotrabcedido.infonus|to_xml:"esocial|N" }}</infOnus>{% endif %}{% endif %}{% if versao in ';;NDE1_NDE2' %}{% if s2300_infotrabcedido.indremuncargo or s2300_infotrabcedido.indremuncargo == 0 %}<indRemunCargo>{{ s2300_infotrabcedido.indremuncargo|to_xml:"esocial|C" }}</indRemunCargo>{% endif %}{% endif %}</infoTrabCedido>{% endifequal %}{% endfor %}{% endif %}{% if versao in 'v02_04_02;v02_05_00;NDE1_NDE2' %}{% query s2300_infoestagiario_lista s2300_infocomplementares=s2300_infocomplementares as s2300_infoestagiario_lista_filtro %}{% for s2300_infoestagiario in s2300_infoestagiario_lista_filtro %}{% ifequal s2300_infoestagiario.s2300_infocomplementares.id s2300_infocomplementares.id %}<infoEstagiario>{% if versao in 'v02_04_02;v02_05_00;NDE1_NDE2' %}{% if s2300_infoestagiario.natestagio or s2300_infoestagiario.natestagio == 0 %}<natEstagio>{{ s2300_infoestagiario.natestagio|to_xml:"esocial|C" }}</natEstagio>{% endif %}{% endif %}{% if versao in 'v02_04_02;v02_05_00;NDE1_NDE2' %}{% if s2300_infoestagiario.nivestagio or s2300_infoestagiario.nivestagio == 0 %}<nivEstagio>{{ s2300_infoestagiario.nivestagio|to_xml:"esocial|N" }}</nivEstagio>{% endif %}{% endif %}{% if versao in 'v02_04_02;v02_05_00;NDE1_NDE2' %}{% if s2300_infoestagiario.areaatuacao or s2300_infoestagiario.areaatuacao == 0 %}<areaAtuacao>{{ s2300_infoestagiario.areaatuacao|to_xml:"esocial|C" }}</areaAtuacao>{% endif %}{% endif %}{% if versao in 'v02_04_02;v02_05_00;NDE1_NDE2' %}{% if s2300_infoestagiario.nrapol or s2300_infoestagiario.nrapol == 0 %}<nrApol>{{ s2300_infoestagiario.nrapol|to_xml:"esocial|C" }}</nrApol>{% endif %}{% endif %}{% if versao in 'v02_04_02;v02_05_00;NDE1_NDE2' %}{% if s2300_infoestagiario.vlrbolsa or s2300_infoestagiario.vlrbolsa == 0 %}<vlrBolsa>{{ s2300_infoestagiario.vlrbolsa|to_xml:"esocial|N" }}</vlrBolsa>{% endif %}{% endif %}{% if versao in 'v02_04_02;v02_05_00;NDE1_NDE2' %}{% if s2300_infoestagiario.dtprevterm or s2300_infoestagiario.dtprevterm == 0 %}<dtPrevTerm>{{ s2300_infoestagiario.dtprevterm|date:"Y-m-d" }}</dtPrevTerm>{% endif %}{% endif %}{% if versao in 'v02_04_02;v02_05_00;NDE1_NDE2' %}<instEnsino>{% if versao in 'v02_04_02;v02_05_00;NDE1_NDE2' %}{% if s2300_infoestagiario.cnpjinstensino or s2300_infoestagiario.cnpjinstensino == 0 %}<cnpjInstEnsino>{{ s2300_infoestagiario.cnpjinstensino|to_xml:"esocial|C" }}</cnpjInstEnsino>{% endif %}{% endif %}{% if versao in 'v02_04_02;v02_05_00;NDE1_NDE2' %}{% if s2300_infoestagiario.nmrazao or s2300_infoestagiario.nmrazao == 0 %}<nmRazao>{{ s2300_infoestagiario.nmrazao|to_xml:"esocial|C" }}</nmRazao>{% endif %}{% endif %}{% if versao in 'v02_04_02;v02_05_00;NDE1_NDE2' %}{% if s2300_infoestagiario.dsclograd or s2300_infoestagiario.dsclograd == 0 %}<dscLograd>{{ s2300_infoestagiario.dsclograd|to_xml:"esocial|C" }}</dscLograd>{% endif %}{% endif %}{% if versao in 'v02_04_02;v02_05_00;NDE1_NDE2' %}{% if s2300_infoestagiario.nrlograd or s2300_infoestagiario.nrlograd == 0 %}<nrLograd>{{ s2300_infoestagiario.nrlograd|to_xml:"esocial|C" }}</nrLograd>{% endif %}{% endif %}{% if versao in 'v02_04_02;v02_05_00;NDE1_NDE2' %}{% if s2300_infoestagiario.bairro or s2300_infoestagiario.bairro == 0 %}<bairro>{{ s2300_infoestagiario.bairro|to_xml:"esocial|C" }}</bairro>{% endif %}{% endif %}{% if versao in 'v02_04_02;v02_05_00;NDE1_NDE2' %}{% if s2300_infoestagiario.cep or s2300_infoestagiario.cep == 0 %}<cep>{{ s2300_infoestagiario.cep|to_xml:"esocial|C" }}</cep>{% endif %}{% endif %}{% if versao in 'v02_04_02;v02_05_00;NDE1_NDE2' %}{% if s2300_infoestagiario.codmunic or s2300_infoestagiario.codmunic == 0 %}<codMunic>{{ s2300_infoestagiario.codmunic|to_xml:"esocial|N" }}</codMunic>{% endif %}{% endif %}{% if versao in 'v02_04_02;v02_05_00;NDE1_NDE2' %}{% if s2300_infoestagiario.uf or s2300_infoestagiario.uf == 0 %}<uf>{{ s2300_infoestagiario.uf|to_xml:"esocial|C" }}</uf>{% endif %}{% endif %}</instEnsino>{% endif %}{% if versao in 'v02_04_02;v02_05_00;NDE1_NDE2' %}{% query s2300_ageintegracao_lista s2300_infoestagiario=s2300_infoestagiario as s2300_ageintegracao_lista_filtro %}{% for s2300_ageintegracao in s2300_ageintegracao_lista_filtro %}{% ifequal s2300_ageintegracao.s2300_infoestagiario.id s2300_infoestagiario.id %}<ageIntegracao>{% if versao in 'v02_04_02;v02_05_00;NDE1_NDE2' %}{% if s2300_ageintegracao.cnpjagntinteg or s2300_ageintegracao.cnpjagntinteg == 0 %}<cnpjAgntInteg>{{ s2300_ageintegracao.cnpjagntinteg|to_xml:"esocial|C" }}</cnpjAgntInteg>{% endif %}{% endif %}{% if versao in 'v02_04_02;v02_05_00;NDE1_NDE2' %}{% if s2300_ageintegracao.nmrazao or s2300_ageintegracao.nmrazao == 0 %}<nmRazao>{{ s2300_ageintegracao.nmrazao|to_xml:"esocial|C" }}</nmRazao>{% endif %}{% endif %}{% if versao in 'v02_04_02;v02_05_00;NDE1_NDE2' %}{% if s2300_ageintegracao.dsclograd or s2300_ageintegracao.dsclograd == 0 %}<dscLograd>{{ s2300_ageintegracao.dsclograd|to_xml:"esocial|C" }}</dscLograd>{% endif %}{% endif %}{% if versao in 'v02_04_02;v02_05_00;NDE1_NDE2' %}{% if s2300_ageintegracao.nrlograd or s2300_ageintegracao.nrlograd == 0 %}<nrLograd>{{ s2300_ageintegracao.nrlograd|to_xml:"esocial|C" }}</nrLograd>{% endif %}{% endif %}{% if versao in 'v02_04_02;v02_05_00;NDE1_NDE2' %}{% if s2300_ageintegracao.bairro or s2300_ageintegracao.bairro == 0 %}<bairro>{{ s2300_ageintegracao.bairro|to_xml:"esocial|C" }}</bairro>{% endif %}{% endif %}{% if versao in 'v02_04_02;v02_05_00;NDE1_NDE2' %}{% if s2300_ageintegracao.cep or s2300_ageintegracao.cep == 0 %}<cep>{{ s2300_ageintegracao.cep|to_xml:"esocial|C" }}</cep>{% endif %}{% endif %}{% if versao in 'v02_04_02;v02_05_00;NDE1_NDE2' %}{% if s2300_ageintegracao.codmunic or s2300_ageintegracao.codmunic == 0 %}<codMunic>{{ s2300_ageintegracao.codmunic|to_xml:"esocial|N" }}</codMunic>{% endif %}{% endif %}{% if versao in 'v02_04_02;v02_05_00;NDE1_NDE2' %}{% if s2300_ageintegracao.uf or s2300_ageintegracao.uf == 0 %}<uf>{{ s2300_ageintegracao.uf|to_xml:"esocial|C" }}</uf>{% endif %}{% endif %}</ageIntegracao>{% endifequal %}{% endfor %}{% endif %}{% if versao in 'v02_04_02;v02_05_00;NDE1_NDE2' %}{% query s2300_supervisorestagio_lista s2300_infoestagiario=s2300_infoestagiario as s2300_supervisorestagio_lista_filtro %}{% for s2300_supervisorestagio in s2300_supervisorestagio_lista_filtro %}{% ifequal s2300_supervisorestagio.s2300_infoestagiario.id s2300_infoestagiario.id %}<supervisorEstagio>{% if versao in 'v02_04_02;v02_05_00;NDE1_NDE2' %}{% if s2300_supervisorestagio.cpfsupervisor or s2300_supervisorestagio.cpfsupervisor == 0 %}<cpfSupervisor>{{ s2300_supervisorestagio.cpfsupervisor|to_xml:"esocial|C" }}</cpfSupervisor>{% endif %}{% endif %}{% if versao in 'v02_04_02;v02_05_00;NDE1_NDE2' %}{% if s2300_supervisorestagio.nmsuperv or s2300_supervisorestagio.nmsuperv == 0 %}<nmSuperv>{{ s2300_supervisorestagio.nmsuperv|to_xml:"esocial|C" }}</nmSuperv>{% endif %}{% endif %}</supervisorEstagio>{% endifequal %}{% endfor %}{% endif %}</infoEstagiario>{% endifequal %}{% endfor %}{% endif %}</infoComplementares>{% endifequal %}{% endfor %}{% endif %}{% if versao in ';v02_05_00;' %}{% query s2300_mudancacpf_lista s2300_evttsvinicio=s2300_evttsvinicio as s2300_mudancacpf_lista_filtro %}{% for s2300_mudancacpf in s2300_mudancacpf_lista_filtro %}{% ifequal s2300_mudancacpf.s2300_evttsvinicio.id s2300_evttsvinicio.id %}<mudancaCPF>{% if versao in ';v02_05_00;' %}{% if s2300_mudancacpf.cpfant or s2300_mudancacpf.cpfant == 0 %}<cpfAnt>{{ s2300_mudancacpf.cpfant|to_xml:"esocial|C" }}</cpfAnt>{% endif %}{% endif %}{% if versao in ';v02_05_00;' %}{% if s2300_mudancacpf.dtaltcpf or s2300_mudancacpf.dtaltcpf == 0 %}<dtAltCPF>{{ s2300_mudancacpf.dtaltcpf|date:"Y-m-d" }}</dtAltCPF>{% endif %}{% endif %}{% if versao in ';v02_05_00;' %}{% if s2300_mudancacpf.observacao or s2300_mudancacpf.observacao == 0 %}<observacao>{{ s2300_mudancacpf.observacao|to_xml:"esocial|C" }}</observacao>{% endif %}{% endif %}</mudancaCPF>{% endifequal %}{% endfor %}{% endif %}{% if versao in 'v02_04_02;v02_05_00;NDE1_NDE2' %}{% query s2300_afastamento_lista s2300_evttsvinicio=s2300_evttsvinicio as s2300_afastamento_lista_filtro %}{% for s2300_afastamento in s2300_afastamento_lista_filtro %}{% ifequal s2300_afastamento.s2300_evttsvinicio.id s2300_evttsvinicio.id %}<afastamento>{% if versao in 'v02_04_02;v02_05_00;NDE1_NDE2' %}{% if s2300_afastamento.dtiniafast or s2300_afastamento.dtiniafast == 0 %}<dtIniAfast>{{ s2300_afastamento.dtiniafast|date:"Y-m-d" }}</dtIniAfast>{% endif %}{% endif %}{% if versao in 'v02_04_02;v02_05_00;NDE1_NDE2' %}{% if s2300_afastamento.codmotafast or s2300_afastamento.codmotafast == 0 %}<codMotAfast>{{ s2300_afastamento.codmotafast|to_xml:"esocial|C" }}</codMotAfast>{% endif %}{% endif %}</afastamento>{% endifequal %}{% endfor %}{% endif %}{% if versao in 'v02_04_02;v02_05_00;NDE1_NDE2' %}{% query s2300_termino_lista s2300_evttsvinicio=s2300_evttsvinicio as s2300_termino_lista_filtro %}{% for s2300_termino in s2300_termino_lista_filtro %}{% ifequal s2300_termino.s2300_evttsvinicio.id s2300_evttsvinicio.id %}<termino>{% if versao in 'v02_04_02;v02_05_00;NDE1_NDE2' %}{% if s2300_termino.dtterm or s2300_termino.dtterm == 0 %}<dtTerm>{{ s2300_termino.dtterm|date:"Y-m-d" }}</dtTerm>{% endif %}{% endif %}</termino>{% endifequal %}{% endfor %}{% endif %}</infoTSVInicio>{% endif %}</evtTSVInicio>{% endifequal %}{% endfor %}</eSocial>