{% load templatetags %}<Reinf xmlns="{{ xmlns }}">{% for r4020_evtretpj in r4020_evtretpj_lista %}{% ifequal 1 1 %}<evtRetPJ id="{{ r4020_evtretpj.identidade }}"><ideEvento>{% if r4020_evtretpj.indretif or r4020_evtretpj.indretif == 0 %}<indRetif>{{ r4020_evtretpj.indretif|to_xml:"efdreinf|N" }}</indRetif>{% endif %}{% if r4020_evtretpj.nrrecibo or r4020_evtretpj.nrrecibo == 0 %}<nrRecibo>{{ r4020_evtretpj.nrrecibo|to_xml:"efdreinf|C" }}</nrRecibo>{% endif %}{% if r4020_evtretpj.perapur or r4020_evtretpj.perapur == 0 %}<perApur>{{ r4020_evtretpj.perapur|to_xml:"efdreinf|C" }}</perApur>{% endif %}{% if r4020_evtretpj.tpamb or r4020_evtretpj.tpamb == 0 %}<tpAmb>{{ r4020_evtretpj.tpamb|to_xml:"efdreinf|N" }}</tpAmb>{% endif %}{% if r4020_evtretpj.procemi or r4020_evtretpj.procemi == 0 %}<procEmi>{{ r4020_evtretpj.procemi|to_xml:"efdreinf|N" }}</procEmi>{% endif %}{% if r4020_evtretpj.verproc or r4020_evtretpj.verproc == 0 %}<verProc>{{ r4020_evtretpj.verproc|to_xml:"efdreinf|C" }}</verProc>{% endif %}</ideEvento><ideContri>{% if r4020_evtretpj.tpinsc or r4020_evtretpj.tpinsc == 0 %}<tpInsc>{{ r4020_evtretpj.tpinsc|to_xml:"efdreinf|N" }}</tpInsc>{% endif %}{% if r4020_evtretpj.nrinsc or r4020_evtretpj.nrinsc == 0 %}<nrInsc>{{ r4020_evtretpj.nrinsc|to_xml:"efdreinf|C" }}</nrInsc>{% endif %}</ideContri><ideEstab>{% if r4020_evtretpj.tpinscestab or r4020_evtretpj.tpinscestab == 0 %}<tpInscEstab>{{ r4020_evtretpj.tpinscestab|to_xml:"efdreinf|N" }}</tpInscEstab>{% endif %}{% if r4020_evtretpj.nrinscestab or r4020_evtretpj.nrinscestab == 0 %}<nrInscEstab>{{ r4020_evtretpj.nrinscestab|to_xml:"efdreinf|C" }}</nrInscEstab>{% endif %}<ideBenef>{% if r4020_evtretpj.cnpjbenef or r4020_evtretpj.cnpjbenef == 0 %}<cnpjBenef>{{ r4020_evtretpj.cnpjbenef|to_xml:"efdreinf|C" }}</cnpjBenef>{% endif %}{% if r4020_evtretpj.nmbenef or r4020_evtretpj.nmbenef == 0 %}<nmBenef>{{ r4020_evtretpj.nmbenef|to_xml:"efdreinf|C" }}</nmBenef>{% endif %}{% if r4020_evtretpj.isenimun or r4020_evtretpj.isenimun == 0 %}<isenImun>{{ r4020_evtretpj.isenimun|to_xml:"efdreinf|N" }}</isenImun>{% endif %}{% query r4020_idepgto_lista r4020_evtretpj=r4020_evtretpj as r4020_idepgto_lista_filtro %}{% for r4020_idepgto in r4020_idepgto_lista_filtro %}{% ifequal r4020_idepgto.r4020_evtretpj.id r4020_evtretpj.id %}<idePgto>{% if r4020_idepgto.natrend or r4020_idepgto.natrend == 0 %}<natRend>{{ r4020_idepgto.natrend|to_xml:"efdreinf|C" }}</natRend>{% endif %}{% if r4020_idepgto.paisresid or r4020_idepgto.paisresid == 0 %}<paisResid>{{ r4020_idepgto.paisresid|to_xml:"efdreinf|C" }}</paisResid>{% endif %}{% if r4020_idepgto.observ or r4020_idepgto.observ == 0 %}<observ>{{ r4020_idepgto.observ|to_xml:"efdreinf|C" }}</observ>{% endif %}{% query r4020_infopgto_lista r4020_idepgto=r4020_idepgto as r4020_infopgto_lista_filtro %}{% for r4020_infopgto in r4020_infopgto_lista_filtro %}{% ifequal r4020_infopgto.r4020_idepgto.id r4020_idepgto.id %}<infoPgto>{% if r4020_infopgto.dtfg or r4020_infopgto.dtfg == 0 %}<dtFG>{{ r4020_infopgto.dtfg|date:"Y-m-d" }}</dtFG>{% endif %}{% if r4020_infopgto.vlrtotalpag or r4020_infopgto.vlrtotalpag == 0 %}<vlrTotalPag>{{ r4020_infopgto.vlrtotalpag|to_xml:"efdreinf|N" }}</vlrTotalPag>{% endif %}{% if r4020_infopgto.vlrtotalcred or r4020_infopgto.vlrtotalcred == 0 %}<vlrTotalCred>{{ r4020_infopgto.vlrtotalcred|to_xml:"efdreinf|N" }}</vlrTotalCred>{% endif %}{% query r4020_ir_lista r4020_infopgto=r4020_infopgto as r4020_ir_lista_filtro %}{% for r4020_ir in r4020_ir_lista_filtro %}{% ifequal r4020_ir.r4020_infopgto.id r4020_infopgto.id %}<IR>{% if r4020_ir.vlrbaseir or r4020_ir.vlrbaseir == 0 %}<vlrBaseIR>{{ r4020_ir.vlrbaseir|to_xml:"efdreinf|N" }}</vlrBaseIR>{% endif %}{% if r4020_ir.vlrir or r4020_ir.vlrir == 0 %}<vlrIR>{{ r4020_ir.vlrir|to_xml:"efdreinf|N" }}</vlrIR>{% endif %}{% if r4020_ir.vlrbasenir or r4020_ir.vlrbasenir == 0 %}<vlrBaseNIR>{{ r4020_ir.vlrbasenir|to_xml:"efdreinf|N" }}</vlrBaseNIR>{% endif %}{% if r4020_ir.vlrnir or r4020_ir.vlrnir == 0 %}<vlrNIR>{{ r4020_ir.vlrnir|to_xml:"efdreinf|N" }}</vlrNIR>{% endif %}{% if r4020_ir.vlrdepir or r4020_ir.vlrdepir == 0 %}<vlrDepIR>{{ r4020_ir.vlrdepir|to_xml:"efdreinf|N" }}</vlrDepIR>{% endif %}</IR>{% endifequal %}{% endfor %}{% query r4020_csll_lista r4020_infopgto=r4020_infopgto as r4020_csll_lista_filtro %}{% for r4020_csll in r4020_csll_lista_filtro %}{% ifequal r4020_csll.r4020_infopgto.id r4020_infopgto.id %}<CSLL>{% if r4020_csll.vlrbasecsll or r4020_csll.vlrbasecsll == 0 %}<vlrBaseCSLL>{{ r4020_csll.vlrbasecsll|to_xml:"efdreinf|N" }}</vlrBaseCSLL>{% endif %}{% if r4020_csll.vlrcsll or r4020_csll.vlrcsll == 0 %}<vlrCSLL>{{ r4020_csll.vlrcsll|to_xml:"efdreinf|N" }}</vlrCSLL>{% endif %}{% if r4020_csll.vlrbasencsll or r4020_csll.vlrbasencsll == 0 %}<vlrBaseNCSLL>{{ r4020_csll.vlrbasencsll|to_xml:"efdreinf|N" }}</vlrBaseNCSLL>{% endif %}{% if r4020_csll.vlrncsll or r4020_csll.vlrncsll == 0 %}<vlrNCSLL>{{ r4020_csll.vlrncsll|to_xml:"efdreinf|N" }}</vlrNCSLL>{% endif %}{% if r4020_csll.vlrdepcsll or r4020_csll.vlrdepcsll == 0 %}<vlrDepCSLL>{{ r4020_csll.vlrdepcsll|to_xml:"efdreinf|N" }}</vlrDepCSLL>{% endif %}</CSLL>{% endifequal %}{% endfor %}{% query r4020_cofins_lista r4020_infopgto=r4020_infopgto as r4020_cofins_lista_filtro %}{% for r4020_cofins in r4020_cofins_lista_filtro %}{% ifequal r4020_cofins.r4020_infopgto.id r4020_infopgto.id %}<Cofins>{% if r4020_cofins.vlrbasecofins or r4020_cofins.vlrbasecofins == 0 %}<vlrBaseCofins>{{ r4020_cofins.vlrbasecofins|to_xml:"efdreinf|N" }}</vlrBaseCofins>{% endif %}{% if r4020_cofins.vlrcofins or r4020_cofins.vlrcofins == 0 %}<vlrCofins>{{ r4020_cofins.vlrcofins|to_xml:"efdreinf|N" }}</vlrCofins>{% endif %}{% if r4020_cofins.vlrbasencofins or r4020_cofins.vlrbasencofins == 0 %}<vlrBaseNCofins>{{ r4020_cofins.vlrbasencofins|to_xml:"efdreinf|N" }}</vlrBaseNCofins>{% endif %}{% if r4020_cofins.vlrncofins or r4020_cofins.vlrncofins == 0 %}<vlrNCofins>{{ r4020_cofins.vlrncofins|to_xml:"efdreinf|N" }}</vlrNCofins>{% endif %}{% if r4020_cofins.vlrdepcofins or r4020_cofins.vlrdepcofins == 0 %}<vlrDepCofins>{{ r4020_cofins.vlrdepcofins|to_xml:"efdreinf|N" }}</vlrDepCofins>{% endif %}</Cofins>{% endifequal %}{% endfor %}{% query r4020_pp_lista r4020_infopgto=r4020_infopgto as r4020_pp_lista_filtro %}{% for r4020_pp in r4020_pp_lista_filtro %}{% ifequal r4020_pp.r4020_infopgto.id r4020_infopgto.id %}<PP>{% if r4020_pp.vlrbasepp or r4020_pp.vlrbasepp == 0 %}<vlrBasePP>{{ r4020_pp.vlrbasepp|to_xml:"efdreinf|N" }}</vlrBasePP>{% endif %}{% if r4020_pp.vlrpp or r4020_pp.vlrpp == 0 %}<vlrPP>{{ r4020_pp.vlrpp|to_xml:"efdreinf|N" }}</vlrPP>{% endif %}{% if r4020_pp.vlrbasenpp or r4020_pp.vlrbasenpp == 0 %}<vlrBaseNPP>{{ r4020_pp.vlrbasenpp|to_xml:"efdreinf|N" }}</vlrBaseNPP>{% endif %}{% if r4020_pp.vlrnpp or r4020_pp.vlrnpp == 0 %}<vlrNPP>{{ r4020_pp.vlrnpp|to_xml:"efdreinf|N" }}</vlrNPP>{% endif %}{% if r4020_pp.vlrdeppp or r4020_pp.vlrdeppp == 0 %}<vlrDepPP>{{ r4020_pp.vlrdeppp|to_xml:"efdreinf|N" }}</vlrDepPP>{% endif %}</PP>{% endifequal %}{% endfor %}{% query r4020_fci_lista r4020_infopgto=r4020_infopgto as r4020_fci_lista_filtro %}{% for r4020_fci in r4020_fci_lista_filtro %}{% ifequal r4020_fci.r4020_infopgto.id r4020_infopgto.id %}<FCI>{% if r4020_fci.nrinscfci or r4020_fci.nrinscfci == 0 %}<nrInscFCI>{{ r4020_fci.nrinscfci|to_xml:"efdreinf|C" }}</nrInscFCI>{% endif %}</FCI>{% endifequal %}{% endfor %}{% query r4020_scp_lista r4020_infopgto=r4020_infopgto as r4020_scp_lista_filtro %}{% for r4020_scp in r4020_scp_lista_filtro %}{% ifequal r4020_scp.r4020_infopgto.id r4020_infopgto.id %}<SCP>{% if r4020_scp.nrinscscp or r4020_scp.nrinscscp == 0 %}<nrInscSCP>{{ r4020_scp.nrinscscp|to_xml:"efdreinf|C" }}</nrInscSCP>{% endif %}{% if r4020_scp.percscp or r4020_scp.percscp == 0 %}<percSCP>{{ r4020_scp.percscp|to_xml:"efdreinf|N" }}</percSCP>{% endif %}</SCP>{% endifequal %}{% endfor %}{% query r4020_infoprocret_lista r4020_infopgto=r4020_infopgto as r4020_infoprocret_lista_filtro %}{% for r4020_infoprocret in r4020_infoprocret_lista_filtro %}{% ifequal r4020_infoprocret.r4020_infopgto.id r4020_infopgto.id %}<infoProcRet>{% if r4020_infoprocret.tpprocret or r4020_infoprocret.tpprocret == 0 %}<tpProcRet>{{ r4020_infoprocret.tpprocret|to_xml:"efdreinf|N" }}</tpProcRet>{% endif %}{% if r4020_infoprocret.nrprocret or r4020_infoprocret.nrprocret == 0 %}<nrProcRet>{{ r4020_infoprocret.nrprocret|to_xml:"efdreinf|C" }}</nrProcRet>{% endif %}{% if r4020_infoprocret.codsusp or r4020_infoprocret.codsusp == 0 %}<codSusp>{{ r4020_infoprocret.codsusp|to_xml:"efdreinf|N" }}</codSusp>{% endif %}{% if r4020_infoprocret.nir or r4020_infoprocret.nir == 0 %}<nIR>{{ r4020_infoprocret.nir|to_xml:"efdreinf|N" }}</nIR>{% endif %}{% if r4020_infoprocret.depir or r4020_infoprocret.depir == 0 %}<depIR>{{ r4020_infoprocret.depir|to_xml:"efdreinf|N" }}</depIR>{% endif %}{% if r4020_infoprocret.ncsll or r4020_infoprocret.ncsll == 0 %}<nCSLL>{{ r4020_infoprocret.ncsll|to_xml:"efdreinf|N" }}</nCSLL>{% endif %}{% if r4020_infoprocret.depcsll or r4020_infoprocret.depcsll == 0 %}<depCSLL>{{ r4020_infoprocret.depcsll|to_xml:"efdreinf|N" }}</depCSLL>{% endif %}{% if r4020_infoprocret.ncofins or r4020_infoprocret.ncofins == 0 %}<nCofins>{{ r4020_infoprocret.ncofins|to_xml:"efdreinf|N" }}</nCofins>{% endif %}{% if r4020_infoprocret.depcofins or r4020_infoprocret.depcofins == 0 %}<depCofins>{{ r4020_infoprocret.depcofins|to_xml:"efdreinf|N" }}</depCofins>{% endif %}{% if r4020_infoprocret.npp or r4020_infoprocret.npp == 0 %}<nPP>{{ r4020_infoprocret.npp|to_xml:"efdreinf|N" }}</nPP>{% endif %}{% if r4020_infoprocret.deppp or r4020_infoprocret.deppp == 0 %}<depPP>{{ r4020_infoprocret.deppp|to_xml:"efdreinf|N" }}</depPP>{% endif %}</infoProcRet>{% endifequal %}{% endfor %}{% query r4020_infoprocjud_lista r4020_infopgto=r4020_infopgto as r4020_infoprocjud_lista_filtro %}{% for r4020_infoprocjud in r4020_infoprocjud_lista_filtro %}{% ifequal r4020_infoprocjud.r4020_infopgto.id r4020_infopgto.id %}<infoProcJud>{% if r4020_infoprocjud.nrproc or r4020_infoprocjud.nrproc == 0 %}<nrProc>{{ r4020_infoprocjud.nrproc|to_xml:"efdreinf|C" }}</nrProc>{% endif %}{% if r4020_infoprocjud.indorigemrecursos or r4020_infoprocjud.indorigemrecursos == 0 %}<indOrigemRecursos>{{ r4020_infoprocjud.indorigemrecursos|to_xml:"efdreinf|N" }}</indOrigemRecursos>{% endif %}{% if r4020_infoprocjud.desc or r4020_infoprocjud.desc == 0 %}<desc>{{ r4020_infoprocjud.desc|to_xml:"efdreinf|C" }}</desc>{% endif %}{% query r4020_despprocjud_lista r4020_infoprocjud=r4020_infoprocjud as r4020_despprocjud_lista_filtro %}{% for r4020_despprocjud in r4020_despprocjud_lista_filtro %}{% ifequal r4020_despprocjud.r4020_infoprocjud.id r4020_infoprocjud.id %}<despProcJud>{% if r4020_despprocjud.vlrdespcustas or r4020_despprocjud.vlrdespcustas == 0 %}<vlrDespCustas>{{ r4020_despprocjud.vlrdespcustas|to_xml:"efdreinf|N" }}</vlrDespCustas>{% endif %}{% if r4020_despprocjud.vlrdespadvogados or r4020_despprocjud.vlrdespadvogados == 0 %}<vlrDespAdvogados>{{ r4020_despprocjud.vlrdespadvogados|to_xml:"efdreinf|N" }}</vlrDespAdvogados>{% endif %}{% query r4020_ideadv_lista r4020_despprocjud=r4020_despprocjud as r4020_ideadv_lista_filtro %}{% for r4020_ideadv in r4020_ideadv_lista_filtro %}{% ifequal r4020_ideadv.r4020_despprocjud.id r4020_despprocjud.id %}<ideAdv>{% if r4020_ideadv.tpinscadv or r4020_ideadv.tpinscadv == 0 %}<tpInscAdv>{{ r4020_ideadv.tpinscadv|to_xml:"efdreinf|N" }}</tpInscAdv>{% endif %}{% if r4020_ideadv.nrinscadv or r4020_ideadv.nrinscadv == 0 %}<nrInscAdv>{{ r4020_ideadv.nrinscadv|to_xml:"efdreinf|C" }}</nrInscAdv>{% endif %}{% if r4020_ideadv.vlradv or r4020_ideadv.vlradv == 0 %}<vlrAdv>{{ r4020_ideadv.vlradv|to_xml:"efdreinf|N" }}</vlrAdv>{% endif %}</ideAdv>{% endifequal %}{% endfor %}</despProcJud>{% endifequal %}{% endfor %}{% query r4020_origemrec_lista r4020_infoprocjud=r4020_infoprocjud as r4020_origemrec_lista_filtro %}{% for r4020_origemrec in r4020_origemrec_lista_filtro %}{% ifequal r4020_origemrec.r4020_infoprocjud.id r4020_infoprocjud.id %}<origemRec>{% if r4020_origemrec.cnpjorigrecurso or r4020_origemrec.cnpjorigrecurso == 0 %}<cnpjOrigRecurso>{{ r4020_origemrec.cnpjorigrecurso|to_xml:"efdreinf|C" }}</cnpjOrigRecurso>{% endif %}</origemRec>{% endifequal %}{% endfor %}</infoProcJud>{% endifequal %}{% endfor %}</infoPgto>{% endifequal %}{% endfor %}{% query r4020_infopgtoext_lista r4020_idepgto=r4020_idepgto as r4020_infopgtoext_lista_filtro %}{% for r4020_infopgtoext in r4020_infopgtoext_lista_filtro %}{% ifequal r4020_infopgtoext.r4020_idepgto.id r4020_idepgto.id %}<infoPgtoExt><endExt>{% if r4020_infopgtoext.dsclograd or r4020_infopgtoext.dsclograd == 0 %}<dscLograd>{{ r4020_infopgtoext.dsclograd|to_xml:"efdreinf|C" }}</dscLograd>{% endif %}{% if r4020_infopgtoext.nrlograd or r4020_infopgtoext.nrlograd == 0 %}<nrLograd>{{ r4020_infopgtoext.nrlograd|to_xml:"efdreinf|C" }}</nrLograd>{% endif %}{% if r4020_infopgtoext.complem or r4020_infopgtoext.complem == 0 %}<complem>{{ r4020_infopgtoext.complem|to_xml:"efdreinf|C" }}</complem>{% endif %}{% if r4020_infopgtoext.bairro or r4020_infopgtoext.bairro == 0 %}<bairro>{{ r4020_infopgtoext.bairro|to_xml:"efdreinf|C" }}</bairro>{% endif %}{% if r4020_infopgtoext.cidade or r4020_infopgtoext.cidade == 0 %}<cidade>{{ r4020_infopgtoext.cidade|to_xml:"efdreinf|C" }}</cidade>{% endif %}{% if r4020_infopgtoext.estado or r4020_infopgtoext.estado == 0 %}<estado>{{ r4020_infopgtoext.estado|to_xml:"efdreinf|C" }}</estado>{% endif %}{% if r4020_infopgtoext.codpostal or r4020_infopgtoext.codpostal == 0 %}<codPostal>{{ r4020_infopgtoext.codpostal|to_xml:"efdreinf|C" }}</codPostal>{% endif %}{% if r4020_infopgtoext.telef or r4020_infopgtoext.telef == 0 %}<telef>{{ r4020_infopgtoext.telef|to_xml:"efdreinf|C" }}</telef>{% endif %}</endExt><infoFiscal>{% if r4020_infopgtoext.indnif or r4020_infopgtoext.indnif == 0 %}<indNIF>{{ r4020_infopgtoext.indnif|to_xml:"efdreinf|N" }}</indNIF>{% endif %}{% if r4020_infopgtoext.nifbenef or r4020_infopgtoext.nifbenef == 0 %}<nifBenef>{{ r4020_infopgtoext.nifbenef|to_xml:"efdreinf|C" }}</nifBenef>{% endif %}{% if r4020_infopgtoext.relfontpg or r4020_infopgtoext.relfontpg == 0 %}<relFontPg>{{ r4020_infopgtoext.relfontpg|to_xml:"efdreinf|N" }}</relFontPg>{% endif %}{% if r4020_infopgtoext.frmtribut or r4020_infopgtoext.frmtribut == 0 %}<frmTribut>{{ r4020_infopgtoext.frmtribut|to_xml:"efdreinf|C" }}</frmTribut>{% endif %}</infoFiscal></infoPgtoExt>{% endifequal %}{% endfor %}</idePgto>{% endifequal %}{% endfor %}</ideBenef></ideEstab></evtRetPJ>{% endifequal %}{% endfor %}</Reinf>